gptvm-0.1.3.dist-info/METADATA
gptvm-0.1.3.dist-info/RECORD
gptvm-0.1.3.dist-info/WHEEL
gptvm-0.1.3.dist-info/entry_points.txt
gptvm-0.1.3.dist-info/top_level.txt
gptvm/__init__.pyc
gptvm/__main__.pyc
gptvm/api.pyc
gptvm/app.pyc
gptvm/cli/__init__.pyc
gptvm/cli/app.pyc
gptvm/cli/auth.pyc
gptvm/cli/cli.pyc
gptvm/cli/env.pyc
gptvm/cli/import_vm.pyc
gptvm/cli/run.pyc
gptvm/cli/runner.pyc
gptvm/cli/runtime.pyc
gptvm/cli/serve.pyc
gptvm/cls.pyc
gptvm/config.pyc
gptvm/function.pyc
gptvm/log.pyc
gptvm/proto/__init__.pyc
gptvm/proto/account_pb2.pyc
gptvm/proto/account_pb2.pyi
gptvm/proto/account_pb2_grpc.pyc
gptvm/proto/api_pb2.pyc
gptvm/proto/api_pb2.pyi
gptvm/proto/api_pb2_grpc.pyc
gptvm/proto/app_pb2.pyc
gptvm/proto/app_pb2.pyi
gptvm/proto/app_pb2_grpc.pyc
gptvm/proto/app_version_pb2.pyc
gptvm/proto/app_version_pb2.pyi
gptvm/proto/app_version_pb2_grpc.pyc
gptvm/proto/common_pb2.pyc
gptvm/proto/common_pb2.pyi
gptvm/proto/common_pb2_grpc.pyc
gptvm/proto/device_pb2.pyc
gptvm/proto/device_pb2.pyi
gptvm/proto/device_pb2_grpc.pyc
gptvm/proto/env_pb2.pyc
gptvm/proto/env_pb2.pyi
gptvm/proto/env_pb2_grpc.pyc
gptvm/proto/hello_pb2.pyc
gptvm/proto/hello_pb2.pyi
gptvm/proto/hello_pb2_grpc.pyc
gptvm/proto/image_pb2.pyc
gptvm/proto/image_pb2.pyi
gptvm/proto/image_pb2_grpc.pyc
gptvm/proto/storage_pb2.pyc
gptvm/proto/storage_pb2.pyi
gptvm/proto/storage_pb2_grpc.pyc
gptvm/proto/task_pb2.pyc
gptvm/proto/task_pb2.pyi
gptvm/proto/task_pb2_grpc.pyc
gptvm/proto/user_pb2.pyc
gptvm/proto/user_pb2.pyi
gptvm/proto/user_pb2_grpc.pyc
gptvm/proto/workgroup_pb2.pyc
gptvm/proto/workgroup_pb2.pyi
gptvm/proto/workgroup_pb2_grpc.pyc
gptvm/proto/workspace_pb2.pyc
gptvm/proto/workspace_pb2.pyi
gptvm/proto/workspace_pb2_grpc.pyc
gptvm/runner/__init__.pyc
gptvm/runner/base.pyc
gptvm/runner/local.pyc
gptvm/runner/remote.pyc
gptvm/vmcfg.pyc
