Metadata-Version: 2.1
Name: gptvm
Version: 0.1.3
Summary: Python client library gptvm
Author: gptvm.ai
Author-email: yong.zhang@unimagix.com
Classifier: Topic :: System :: Distributed Computing
Classifier: Operating System :: OS Independent
Classifier: License :: OSI Approved :: MIT License
Classifier: Programming Language :: Python :: 3
Requires-Python: >=3.7
Requires-Dist: grpcio
Requires-Dist: protobuf
Requires-Dist: dataclasses
Requires-Dist: typer
Requires-Dist: click
Requires-Dist: requests
Requires-Dist: fastapi
Requires-Dist: uvicorn
